comun_saplogon.py
comun_saplogon-0.16.dist-info/METADATA
comun_saplogon-0.16.dist-info/WHEEL
comun_saplogon-0.16.dist-info/top_level.txt
comun_saplogon-0.16.dist-info/RECORD
