Metadata-Version: 2.1
Name: comun-saplogon
Version: 0.16
Summary: UNKNOWN
Home-page: UNKNOWN
License: UNKNOWN
Platform: UNKNOWN
Requires-Dist: pywin32
Requires-Dist: pyscreeze
Requires-Dist: pillow
